MANIFEST.in
README.rst
ez_setup.py
setup.py
cassandra_driver_dse.egg-info/PKG-INFO
cassandra_driver_dse.egg-info/SOURCES.txt
cassandra_driver_dse.egg-info/dependency_links.txt
cassandra_driver_dse.egg-info/requires.txt
cassandra_driver_dse.egg-info/top_level.txt
dse/__init__.py
dse/auth.py
dse/cluster.py
dse/cqltypes.py
dse/graph.py
dse/marshal.py
dse/policies.py
dse/query.py
dse/util.py