Metadata-Version: 1.1
Name: cassandra-driver-dse
Version: 1.1.0
Summary: DataStax Enterprise extensions for cassandra-driver
Home-page: UNKNOWN
Author: UNKNOWN
Author-email: UNKNOWN
License: DataStax DSE Driver License http://www.datastax.com/terms/datastax-dse-driver-license-terms
Keywords: cassandra,dse,graph
Platform: UNKNOWN
Classifier: Development Status :: 5 - Production/Stable
Classifier: Intended Audience :: Developers
Classifier: License :: Other/Proprietary License
Classifier: Natural Language :: English
Classifier: Operating System :: OS Independent
Classifier: Programming Language :: Python
Classifier: Programming Language :: Python :: 2.6
Classifier: Programming Language :: Python :: 2.7
Classifier: Programming Language :: Python :: 3.3
Classifier: Programming Language :: Python :: 3.4
Classifier: Programming Language :: Python :: Implementation :: CPython
Classifier: Programming Language :: Python :: Implementation :: PyPy
Classifier: Topic :: Software Development :: Libraries :: Python Modules
